starccato_lvk/__init__.py
starccato_lvk/_version.py
starccato_lvk/arviz_utils.py
starccato_lvk/constants.py
starccato_lvk/jax_utils.py
starccato_lvk/likelihood.py
starccato_lvk/lvk_data_prep.py
starccato_lvk/main.py
starccato_lvk/data_acquisition/README.md
starccato_lvk/data_acquisition/__init__.py
starccato_lvk/data_acquisition/config.py
starccato_lvk/data_acquisition/lvk_fetch.py
starccato_lvk/data_acquisition/main.py
starccato_lvk/data_acquisition/io/__init__.py
starccato_lvk/data_acquisition/io/determine_valid_segments.py
starccato_lvk/data_acquisition/io/event_catalog.py
starccato_lvk/data_acquisition/io/glitch_catalog.py
starccato_lvk/data_acquisition/io/inject_signal_into_noise.py
starccato_lvk/data_acquisition/io/only_noise_data.py
starccato_lvk/data_acquisition/io/plotting.py
starccato_lvk/data_acquisition/io/strain_loader.py
starccato_lvk/data_acquisition/io/utils.py
starccato_lvk/data_acquisition/io/data/README.md
starccato_lvk/data_acquisition/io/data/only_noise_segments.txt
starccato_lvk/post_proc/__init__.py
starccato_lvk/post_proc/plot_diagnostics.py
starccato_lvk/post_proc/plot_posterior_predictive.py
starccato_lvk-0.0.2.dist-info/METADATA
starccato_lvk-0.0.2.dist-info/WHEEL
starccato_lvk-0.0.2.dist-info/entry_points.txt
starccato_lvk-0.0.2.dist-info/top_level.txt
starccato_lvk-0.0.2.dist-info/RECORD
